odoo/addons/web_tree_many2one_clickable/README.rst
odoo/addons/web_tree_many2one_clickable/__init__.py
odoo/addons/web_tree_many2one_clickable/__manifest__.py
odoo/addons/web_tree_many2one_clickable/i18n/it.po
odoo/addons/web_tree_many2one_clickable/i18n/web_tree_many2one_clickable.pot
odoo/addons/web_tree_many2one_clickable/i18n/zh_CN.po
odoo/addons/web_tree_many2one_clickable/readme/CONFIGURE.md
odoo/addons/web_tree_many2one_clickable/readme/CONTRIBUTORS.md
odoo/addons/web_tree_many2one_clickable/readme/DESCRIPTION.md
odoo/addons/web_tree_many2one_clickable/readme/ROADMAP.md
odoo/addons/web_tree_many2one_clickable/readme/USAGE.md
odoo/addons/web_tree_many2one_clickable/static/description/icon.png
odoo/addons/web_tree_many2one_clickable/static/description/index.html
odoo/addons/web_tree_many2one_clickable/static/img/clickable.gif
odoo/addons/web_tree_many2one_clickable/static/src/components/many2one_button/many2one_button.esm.js
odoo/addons/web_tree_many2one_clickable/static/src/components/many2one_button/many2one_button.scss
odoo/addons/web_tree_many2one_clickable/static/src/components/many2one_button/many2one_button.xml
odoo_addon_web_tree_many2one_clickable-18.0.1.0.1.dist-info/METADATA
odoo_addon_web_tree_many2one_clickable-18.0.1.0.1.dist-info/WHEEL
odoo_addon_web_tree_many2one_clickable-18.0.1.0.1.dist-info/top_level.txt
odoo_addon_web_tree_many2one_clickable-18.0.1.0.1.dist-info/RECORD
