Metadata-Version: 2.1
Name: odoo-addon-web_tree_many2one_clickable
Version: 18.0.1.0.1
Requires-Python: >=3.10
Requires-Dist: odoo==18.0.*
Summary: Open the linked resource when clicking on their name
Home-page: https://github.com/OCA/web
License: AGPL-3
Author: Therp BV, Tecnativa, Camptocamp, Onestein, Odoo Community Association (OCA)
Author-email: support@odoo-community.org
Classifier: Programming Language :: Python
Classifier: Framework :: Odoo
Classifier: Framework :: Odoo :: 18.0
Classifier: License :: OSI Approved :: GNU Affero General Public License v3
